pkman/__init__.py
pkman/apis.py
pkman/clitools/__init__.py
pkman/clitools/apis.py
pkman/clitools/cli.py
pkman/clitools/config.py
pkman/clitools/package.py
pkman/clitools/pkfire.py
pkman/clitools/pkx.py
pkman/clitools/utils/AppDataManager.py
pkman/clitools/utils/CmdUtil.py
pkman/clitools/utils/FireUtil.py
pkman/clitools/utils/IoUtil.py
pkman/clitools/utils/Jinja2Util.py
pkman/clitools/utils/OsUtil.py
pkman/clitools/utils/PathUtil.py
pkman/clitools/utils/SetupUtil.py
pkman/clitools/utils/StringUtil.py
pkman/clitools/utils/__init__.py
pkman-0.1.2.4.dist-info/LICENSE
pkman-0.1.2.4.dist-info/METADATA
pkman-0.1.2.4.dist-info/WHEEL
pkman-0.1.2.4.dist-info/entry_points.txt
pkman-0.1.2.4.dist-info/top_level.txt
pkman-0.1.2.4.dist-info/RECORD
