Metadata-Version: 2.1
Name: pkman
Version: 0.1.2.4
Summary: A python package manager inspired by npm.
Home-page: https://gitee.com/peiiii/pkman
Author: Wang Pei
Author-email: 1535376447@qq.com
License: UNKNOWN
Platform: UNKNOWN
Classifier: Programming Language :: Python :: 3
Classifier: License :: OSI Approved :: MIT License
Classifier: Operating System :: OS Independent
Requires-Python: >=3.0
Requires-Dist: fire
Requires-Dist: codemaker (>=0.0.2.1)
Requires-Dist: codetmpl (>=0.0.1.2)
Requires-Dist: build
Requires-Dist: twine
Requires-Dist: requests
Requires-Dist: freehub (>=0.1.3.5)
